TKinterManagedFrame/ManagedFrame.py
TKinterManagedFrame-0.1.0.dist-info/LICENSE.txt
TKinterManagedFrame-0.1.0.dist-info/METADATA
TKinterManagedFrame-0.1.0.dist-info/WHEEL
TKinterManagedFrame-0.1.0.dist-info/top_level.txt
TKinterManagedFrame-0.1.0.dist-info/RECORD
