Metadata-Version: 2.1
Name: TKinterManagedFrame
Version: 0.1.0
Summary: Adds a Tkinter Frame class that offers simple update functionality
Home-page: https://github.com/ChristopherJTrent/TKinterManagedFrame
Author: Christopher "Arkevorkhat" Trent
License: GNU GPL
Platform: UNKNOWN
Classifier: Development Status :: 3 - Alpha
Classifier: Intended Audience :: Developers
Classifier: Topic :: Software Development :: Libraries :: Tcl Extensions
Classifier: License :: OSI Approved :: GNU General Public License v3 (GPLv3)
Classifier: Natural Language :: English
Classifier: Programming Language :: Python :: 3.3
Classifier: Programming Language :: Python :: 3.4
Classifier: Programming Language :: Python :: 3.5
Classifier: Programming Language :: Python :: 3.6
Classifier: Programming Language :: Python :: 3.7
Classifier: Programming Language :: Python :: 3.8
Classifier: Programming Language :: Python :: 3.9
Requires-Python: >=3.3
Requires-Dist: tkinter
Requires-Dist: wheel
